Workbook

Sheet README
A1: PR. 1 Fundamental Booster — Excel Project
A3: Project Goal: Complete the supplied Student, Sales and Employee datasets using fundamental Excel formulas and formatting.
A4: Sheets included: Students, Sales, Employees, Functions, README.
A5: Students: IF grading, COUNTIFS, IF+AND, FILTER, AVERAGEIFS and date calculations.
A6: Sales: IF discount, VLOOKUP, XLOOKUP, SUMIFS, AVERAGEIFS, INDEX/MATCH, XMATCH, INDIRECT and OFFSET.
A7: Employees: XLOOKUP salary/name/department, joining-date analysis, years of service and salary band.
A8: Functions: Reference formulas and examples for TEXT/string, lookup, date, math and dynamic-reference functions.
A9: Important: Formulas are intentionally visible in cells so the workbook can be used as a learning/project submission file.
A10: Source basis: PR. 1 Fundamental Booster Project Instructions and the supplied Employee, Sales and Students Grade datasets.

Sheet Students
A1: Students Grade Analysis
A3: Student ID | B3: Name | C3: Math | D3: Science | E3: English | F3: Enrollment Date | G3: Grade | H3: Math > 60 | I3: Math & Science > 80 | J3: Age/Years Since Enrollment
A4: 1001 | B4: Student 1 | C4: 61 | D4: 48 | E4: 76 | F4: 43101 | G4: =IF(AVERAGE(C4:E4)>=80,"A",IF(AVERAGE(C4:E4)>=60,"B",IF(AVERAGE(C4:E4)>=50,"C","D"))) | H4: =IF(C4>60,"Yes","No") | I4: =IF(AND(C4>80,D4>80),"Eligible","Not Eligible") | J4: =DATEDIF(F4,TODAY(),"Y")
A5: 1002 | B5: Student 2 | C5: 78 | D5: 76 | E5: 70 | F5: 43281 | G5: =IF(AVERAGE(C5:E5)>=80,"A",IF(AVERAGE(C5:E5)>=60,"B",IF(AVERAGE(C5:E5)>=50,"C","D"))) | H5: =IF(C5>60,"Yes","No") | I5: =IF(AND(C5>80,D5>80),"Eligible","Not Eligible") | J5: =DATEDIF(F5,TODAY(),"Y")
A6: 1003 | B6: Student 3 | C6: 97 | D6: 60 | E6: 51 | F6: 43461 | G6: =IF(AVERAGE(C6:E6)>=80,"A",IF(AVERAGE(C6:E6)>=60,"B",IF(AVERAGE(C6:E6)>=50,"C","D"))) | H6: =IF(C6>60,"Yes","No") | I6: =IF(AND(C6>80,D6>80),"Eligible","Not Eligible") | J6: =DATEDIF(F6,TODAY(),"Y")
A7: 1004 | B7: Student 4 | C7: 74 | D7: 55 | E7: 46 | F7: 43641 | G7: =IF(AVERAGE(C7:E7)>=80,"A",IF(AVERAGE(C7:E7)>=60,"B",IF(AVERAGE(C7:E7)>=50,"C","D"))) | H7: =IF(C7>60,"Yes","No") | I7: =IF(AND(C7>80,D7>80),"Eligible","Not Eligible") | J7: =DATEDIF(F7,TODAY(),"Y")
A8: 1005 | B8: Student 5 | C8: 68 | D8: 74 | E8: 84 | F8: 43821 | G8: =IF(AVERAGE(C8:E8)>=80,"A",IF(AVERAGE(C8:E8)>=60,"B",IF(AVERAGE(C8:E8)>=50,"C","D"))) | H8: =IF(C8>60,"Yes","No") | I8: =IF(AND(C8>80,D8>80),"Eligible","Not Eligible") | J8: =DATEDIF(F8,TODAY(),"Y")
A9: 1006 | B9: Student 6 | C9: 80 | D9: 70 | E9: 65 | F9: 44001 | G9: =IF(AVERAGE(C9:E9)>=80,"A",IF(AVERAGE(C9:E9)>=60,"B",IF(AVERAGE(C9:E9)>=50,"C","D"))) | H9: =IF(C9>60,"Yes","No") | I9: =IF(AND(C9>80,D9>80),"Eligible","Not Eligible") | J9: =DATEDIF(F9,TODAY(),"Y")
A10: 1007 | B10: Student 7 | C10: 75 | D10: 47 | E10: 78 | F10: 44181 | G10: =IF(AVERAGE(C10:E10)>=80,"A",IF(AVERAGE(C10:E10)>=60,"B",IF(AVERAGE(C10:E10)>=50,"C","D"))) | H10: =IF(C10>60,"Yes","No") | I10: =IF(AND(C10>80,D10>80),"Eligible","Not Eligible") | J10: =DATEDIF(F10,TODAY(),"Y")
A11: 1008 | B11: Student 8 | C11: 94 | D11: 67 | E11: 64 | F11: 44361 | G11: =IF(AVERAGE(C11:E11)>=80,"A",IF(AVERAGE(C11:E11)>=60,"B",IF(AVERAGE(C11:E11)>=50,"C","D"))) | H11: =IF(C11>60,"Yes","No") | I11: =IF(AND(C11>80,D11>80),"Eligible","Not Eligible") | J11: =DATEDIF(F11,TODAY(),"Y")
A12: 1009 | B12: Student 9 | C12: 41 | D12: 75 | E12: 56 | F12: 44541 | G12: =IF(AVERAGE(C12:E12)>=80,"A",IF(AVERAGE(C12:E12)>=60,"B",IF(AVERAGE(C12:E12)>=50,"C","D"))) | H12: =IF(C12>60,"Yes","No") | I12: =IF(AND(C12>80,D12>80),"Eligible","Not Eligible") | J12: =DATEDIF(F12,TODAY(),"Y")
A13: 1010 | B13: Student 10 | C13: 98 | D13: 54 | E13: 58 | F13: 44721 | G13: =IF(AVERAGE(C13:E13)>=80,"A",IF(AVERAGE(C13:E13)>=60,"B",IF(AVERAGE(C13:E13)>=50,"C","D"))) | H13: =IF(C13>60,"Yes","No") | I13: =IF(AND(C13>80,D13>80),"Eligible","Not Eligible") | J13: =DATEDIF(F13,TODAY(),"Y")
A14: 1011 | B14: Student 11 | C14: 73 | D14: 79 | E14: 53 | F14: 44901 | G14: =IF(AVERAGE(C14:E14)>=80,"A",IF(AVERAGE(C14:E14)>=60,"B",IF(AVERAGE(C14:E14)>=50,"C","D"))) | H14: =IF(C14>60,"Yes","No") | I14: =IF(AND(C14>80,D14>80),"Eligible","Not Eligible") | J14: =DATEDIF(F14,TODAY(),"Y")
A15: 1012 | B15: Student 12 | C15: 85 | D15: 89 | E15: 79 | F15: 45081 | G15: =IF(AVERAGE(C15:E15)>=80,"A",IF(AVERAGE(C15:E15)>=60,"B",IF(AVERAGE(C15:E15)>=50,"C","D"))) | H15: =IF(C15>60,"Yes","No") | I15: =IF(AND(C15>80,D15>80),"Eligible","Not Eligible") | J15: =DATEDIF(F15,TODAY(),"Y")
... A23: 1020 | B23: Student 20 | C23: 83 | D23: 92 | E23: 55 | F23: 46521 | G23: =IF(AVERAGE(C23:E23)>=80,"A",IF(AVERAGE(C23:E23)>=60,"B",IF(AVERAGE(C23:E23)>=50,"C","D"))) | H23: =IF(C23>60,"Yes","No") | I23: =IF(AND(C23>80,D23>80),"Eligible","Not Eligible") | J23: =DATEDIF(F23,TODAY(),"Y")
A26: Student Analysis Summary
A27: Students with Math > 60 | B27: =COUNTIFS(C4:C23,">60)
A28: Average score of students with Math > 60 | B28: =AVERAGEIFS(C4:C23,C4:C23,">60)
A29: Students with Math & Science > 80 | B29: =COUNTIFS(C4:C23,">80",D4:D23,">80)
A31: FILTER: Students with average score > 80
A32: =FILTER(A4:J23,(C4:C23+D4:D23+E4:E23)/3>80,"No students")

Sheet Sales
A1: Sales Analysis
A3: Sales ID | B3: Product | C3: Region | D3: Salesperson | E3: Amount | F3: Date | G3: Discount % | H3: Discount Amount | I3: Net Sales | K3: Product | L3: Price
A4: 2001 | B4: Keyboard | C4: South | D4: Person 1 | E4: 7048 | F4: 44927 | G4: =IF(E4>=40000,10%,IF(E4>=20000,5%,0%)) | H4: =E4*G4 | I4: =E4-H4 | K4: Keyboard | L4: 1200
A5: 2002 | B5: Printer | C5: West | D5: Person 2 | E5: 17428 | F5: 44942 | G5: =IF(E5>=40000,10%,IF(E5>=20000,5%,0%)) | H5: =E5*G5 | I5: =E5-H5 | K5: Printer | L5: 8500
A6: 2003 | B6: Mouse | C6: South | D6: Person 3 | E6: 23672 | F6: 44957 | G6: =IF(E6>=40000,10%,IF(E6>=20000,5%,0%)) | H6: =E6*G6 | I6: =E6-H6 | K6: Mouse | L6: 700
A7: 2004 | B7: Printer | C7: East | D7: Person 4 | E7: 5264 | F7: 44972 | G7: =IF(E7>=40000,10%,IF(E7>=20000,5%,0%)) | H7: =E7*G7 | I7: =E7-H7 | K7: Monitor | L7: 15000
A8: 2005 | B8: Keyboard | C8: North | D8: Person 5 | E8: 43388 | F8: 44987 | G8: =IF(E8>=40000,10%,IF(E8>=20000,5%,0%)) | H8: =E8*G8 | I8: =E8-H8 | K8: Laptop | L8: 55000
A9: 2006 | B9: Mouse | C9: North | D9: Person 6 | E9: 19757 | F9: 45002 | G9: =IF(E9>=40000,10%,IF(E9>=20000,5%,0%)) | H9: =E9*G9 | I9: =E9-H9
A10: 2007 | B10: Mouse | C10: East | D10: Person 7 | E10: 32058 | F10: 45017 | G10: =IF(E10>=40000,10%,IF(E10>=20000,5%,0%)) | H10: =E10*G10 | I10: =E10-H10
A11: 2008 | B11: Keyboard | C11: East | D11: Person 8 | E11: 46429 | F11: 45032 | G11: =IF(E11>=40000,10%,IF(E11>=20000,5%,0%)) | H11: =E11*G11 | I11: =E11-H11 | K11: VLOOKUP Product Price | L11: =VLOOKUP(B4,$K$4:$L$8,2,FALSE)
A12: 2009 | B12: Printer | C12: East | D12: Person 9 | E12: 19746 | F12: 45047 | G12: =IF(E12>=40000,10%,IF(E12>=20000,5%,0%)) | H12: =E12*G12 | I12: =E12-H12 | K12: XLOOKUP Product Price | L12: =XLOOKUP(B4,$K$4:$K$8,$L$4:$L$8,"Not Found")
A13: 2010 | B13: Keyboard | C13: South | D13: Person 10 | E13: 35185 | F13: 45062 | G13: =IF(E13>=40000,10%,IF(E13>=20000,5%,0%)) | H13: =E13*G13 | I13: =E13-H13 | K13: XMATCH Product Position | L13: =XMATCH(B4,$K$4:$K$8)
A14: 2011 | B14: Keyboard | C14: East | D14: Person 11 | E14: 33920 | F14: 45077 | G14: =IF(E14>=40000,10%,IF(E14>=20000,5%,0%)) | H14: =E14*G14 | I14: =E14-H14
A15: 2012 | B15: Monitor | C15: North | D15: Person 12 | E15: 35611 | F15: 45092 | G15: =IF(E15>=40000,10%,IF(E15>=20000,5%,0%)) | H15: =E15*G15 | I15: =E15-H15 | K15: SUMIFS South Keyboard | L15: =SUMIFS(E4:E23,C4:C23,"South",B4:B23,"Keyboard")
A16: 2013 | B16: Laptop | C16: East | D16: Person 13 | E16: 15560 | F16: 45107 | G16: =IF(E16>=40000,10%,IF(E16>=20000,5%,0%)) | H16: =E16*G16 | I16: =E16-H16 | K16: AVERAGEIFS East | L16: =AVERAGEIFS(E4:E23,C4:C23,"East")
A17: 2014 | B17: Laptop | C17: South | D17: Person 14 | E17: 7283 | F17: 45122 | G17: =IF(E17>=40000,10%,IF(E17>=20000,5%,0%)) | H17: =E17*G17 | I17: =E17-H17
A18: 2015 | B18: Laptop | C18: East | D18: Person 15 | E18: 15678 | F18: 45137 | G18: =IF(E18>=40000,10%,IF(E18>=20000,5%,0%)) | H18: =E18*G18 | I18: =E18-H18 | K18: INDEX/MATCH Person 10 | L18: =INDEX(E4:E23,MATCH("Person 10",D4:D23,0))
A19: 2016 | B19: Mouse | C19: East | D19: Person 16 | E19: 5277 | F19: 45152 | G19: =IF(E19>=40000,10%,IF(E19>=20000,5%,0%)) | H19: =E19*G19 | I19: =E19-H19
A20: 2017 | B20: Monitor | C20: North | D20: Person 17 | E20: 41871 | F20: 45167 | G20: =IF(E20>=40000,10%,IF(E20>=20000,5%,0%)) | H20: =E20*G20 | I20: =E20-H20 | K20: INDIRECT Amount first row | L20: =INDIRECT("E4")
A21: 2018 | B21: Monitor | C21: West | D21: Person 18 | E21: 38161 | F21: 45182 | G21: =IF(E21>=40000,10%,IF(E21>=20000,5%,0%)) | H21: =E21*G21 | I21: =E21-H21 | K21: OFFSET Amount 2 rows down | L21: =OFFSET(E4,2,0)
A22: 2019 | B22: Mouse | C22: West | D22: Person 19 | E22: 30436 | F22: 45197 | G22: =IF(E22>=40000,10%,IF(E22>=20000,5%,0%)) | H22: =E22*G22 | I22: =E22-H22
A23: 2020 | B23: Printer | C23: West | D23: Person 20 | E23: 33953 | F23: 45212 | G23: =IF(E23>=40000,10%,IF(E23>=20000,5%,0%)) | H23: =E23*G23 | I23: =E23-H23

Sheet Employees
A1: Employee Analysis
A3: Employee ID | B3: Name | C3: Department | D3: Salary | E3: Joining Date | F3: Years of Service | G3: Salary Band | I3: Lookup | J3: Result
A4: 3001 | B4: Employee 1 | C4: Finance | D4: 86766 | E4: 42005 | F4: =DATEDIF(E4,TODAY(),"Y") | G4: =IF(D4>=100000,"High",IF(D4>=60000,"Medium","Low")) | I4: Employee ID | J4: 3008
A5: 3002 | B5: Employee 2 | C5: Finance | D5: 31943 | E5: 42255 | F5: =DATEDIF(E5,TODAY(),"Y") | G5: =IF(D5>=100000,"High",IF(D5>=60000,"Medium","Low")) | I5: XLOOKUP Salary | J5: =XLOOKUP(J4,A4:A23,D4:D23,"Not Found")
A6: 3003 | B6: Employee 3 | C6: HR | D6: 63374 | E6: 42505 | F6: =DATEDIF(E6,TODAY(),"Y") | G6: =IF(D6>=100000,"High",IF(D6>=60000,"Medium","Low")) | I6: XLOOKUP Name | J6: =XLOOKUP(J4,A4:A23,B4:B23,"Not Found")
A7: 3004 | B7: Employee 4 | C7: Finance | D7: 109972 | E7: 42755 | F7: =DATEDIF(E7,TODAY(),"Y") | G7: =IF(D7>=100000,"High",IF(D7>=60000,"Medium","Low")) | I7: XLOOKUP Department | J7: =XLOOKUP(J4,A4:A23,C4:C23,"Not Found")
A8: 3005 | B8: Employee 5 | C8: IT | D8: 54149 | E8: 43005 | F8: =DATEDIF(E8,TODAY(),"Y") | G8: =IF(D8>=100000,"High",IF(D8>=60000,"Medium","Low"))
A9: 3006 | B9: Employee 6 | C9: IT | D9: 78689 | E9: 43255 | F9: =DATEDIF(E9,TODAY(),"Y") | G9: =IF(D9>=100000,"High",IF(D9>=60000,"Medium","Low"))
A10: 3007 | B10: Employee 7 | C10: Marketing | D10: 35960 | E10: 43505 | F10: =DATEDIF(E10,TODAY(),"Y") | G10: =IF(D10>=100000,"High",IF(D10>=60000,"Medium","Low"))
A11: 3008 | B11: Employee 8 | C11: IT | D11: 91659 | E11: 43755 | F11: =DATEDIF(E11,TODAY(),"Y") | G11: =IF(D11>=100000,"High",IF(D11>=60000,"Medium","Low"))
A12: 3009 | B12: Employee 9 | C12: IT | D12: 90423 | E12: 44005 | F12: =DATEDIF(E12,TODAY(),"Y") | G12: =IF(D12>=100000,"High",IF(D12>=60000,"Medium","Low"))
A13: 3010 | B13: Employee 10 | C13: HR | D13: 107877 | E13: 44255 | F13: =DATEDIF(E13,TODAY(),"Y") | G13: =IF(D13>=100000,"High",IF(D13>=60000,"Medium","Low"))
A14: 3011 | B14: Employee 11 | C14: Finance | D14: 107634 | E14: 44505 | F14: =DATEDIF(E14,TODAY(),"Y") | G14: =IF(D14>=100000,"High",IF(D14>=60000,"Medium","Low"))
A15: 3012 | B15: Employee 12 | C15: Finance | D15: 35226 | E15: 44755 | F15: =DATEDIF(E15,TODAY(),"Y") | G15: =IF(D15>=100000,"High",IF(D15>=60000,"Medium","Low"))
A16: 3013 | B16: Employee 13 | C16: HR | D16: 40872 | E16: 45005 | F16: =DATEDIF(E16,TODAY(),"Y") | G16: =IF(D16>=100000,"High",IF(D16>=60000,"Medium","Low"))
A17: 3014 | B17: Employee 14 | C17: HR | D17: 55378 | E17: 45255 | F17: =DATEDIF(E17,TODAY(),"Y") | G17: =IF(D17>=100000,"High",IF(D17>=60000,"Medium","Low"))
A18: 3015 | B18: Employee 15 | C18: HR | D18: 63297 | E18: 45505 | F18: =DATEDIF(E18,TODAY(),"Y") | G18: =IF(D18>=100000,"High",IF(D18>=60000,"Medium","Low"))
A19: 3016 | B19: Employee 16 | C19: Finance | D19: 114173 | E19: 45755 | F19: =DATEDIF(E19,TODAY(),"Y") | G19: =IF(D19>=100000,"High",IF(D19>=60000,"Medium","Low"))
... A23: 3020 | B23: Employee 20 | C23: Marketing | D23: 99924 | E23: 46755 | F23: =DATEDIF(E23,TODAY(),"Y") | G23: =IF(D23>=100000,"High",IF(D23>=60000,"Medium","Low"))

Sheet Functions
A1: Excel Fundamental Functions Practice
A3: Function | B3: Purpose | C3: Example Formula | D3: Result / Usage
A4: IF | B4: Conditional classification | C4: =IF(85>=80,"A","B") | D4: A
A5: IF + AND | B5: Multiple conditions | C5: =IF(AND(90>80,85>80),"Eligible","No") | D5: Eligible
A6: IF + OR | B6: Either condition | C6: =IF(OR(90>80,50>80),"Eligible","No") | D6: Eligible
A7: COUNTIFS | B7: Count multiple criteria | C7: =COUNTIFS(Students!C4:C23,">60") | D7: Student count
A8: SUMIFS | B8: Sum with conditions | C8: =SUMIFS(Sales!E4:E23,Sales!C4:C23,"South") | D8: Sales total
A9: AVERAGEIFS | B9: Average with criteria | C9: =AVERAGEIFS(Sales!E4:E23,Sales!C4:C23,"East") | D9: Average
A10: VLOOKUP | B10: Vertical lookup | C10: =VLOOKUP("Laptop",Sales!K4:L8,2,FALSE) | D10: Product price
A11: XLOOKUP | B11: Flexible lookup | C11: =XLOOKUP(3008,Employees!A4:A23,Employees!D4:D23) | D11: Employee salary
A12: INDEX/MATCH | B12: Dynamic lookup | C12: =INDEX(Sales!E4:E23,MATCH("Person 10",Sales!D4:D23,0)) | D12: Sales value
A13: LEFT + FIND | B13: Extract first name | C13: =LEFT("John Smith",FIND(" ","John Smith")-1) | D13: John
A14: UPPER | B14: Uppercase text | C14: =UPPER("excel") | D14: EXCEL
A15: LOWER | B15: Lowercase text | C15: =LOWER("EXCEL") | D15: excel
A16: XMATCH | B16: Find position | C16: =XMATCH("Laptop",Sales!K4:K8) | D16: Position
A17: INDIRECT | B17: Dynamic reference | C17: =INDIRECT("E4") | D17: Cell value
A18: OFFSET | B18: Dynamic range/reference | C18: =OFFSET(Sales!E4,2,0) | D18: Cell value
A19: DATEDIF | B19: Date difference | C19: =DATEDIF(DATE(2018,1,1),TODAY(),"Y") | D19: Years
A20: ROUND | B20: Round number | C20: =ROUND(1234.567,2) | D20: 1234.57
A21: CEILING | B21: Round upward | C21: =CEILING(1234.1,100) | D21: 1300
A22: FLOOR | B22: Round downward | C22: =FLOOR(1234.9,100) | D22: 1200
A23: FILTER | B23: Return matching rows | C23: =FILTER(Students!A4:J23,(Students!C4:C23+Students!D4:D23+Students!E4:E23)/3>80,"No students") | D23: Top students
